<?xml version="1.0" encoding="utf-8"?>
<AuditFile>
  <Header>
    <AuditFileVersion>1.01_01</AuditFileVersion>
    <CompanyID>5111040030</CompanyID>
    <TaxRegistrationNumber>5111053816</TaxRegistrationNumber>
    <TaxAccountingBasis>F</TaxAccountingBasis>
    <CompanyName>MACTOSCOHEM, LDA</CompanyName>
    <BusinessName>TECNOLOGIA E SERVIÇOS, LDA</BusinessName>
    <CompanyAddress>
      <BuildingNumber>F</BuildingNumber>
      <StreetName>Rua</StreetName>
      <AddressDetail>Benguela_Angola</AddressDetail>
      <City>Benguela</City>
      <PostalCode>0</PostalCode>
      <Province>Benguela</Province>
      <Country>AO</Country>
    </CompanyAddress>
    <FiscalYear>2020</FiscalYear>
    <StartDate>2020-02-01</StartDate>
    <EndDate>2020-02-29</EndDate>
    <CurrencyCode>AOA</CurrencyCode>
    <DateCreated>2020-02-20</DateCreated>
    <TaxEntity>Geral</TaxEntity>
    <ProductCompanyTaxID>003136359BA034</ProductCompanyTaxID>
    <SoftwareValidationNumber>230/AGT/2019</SoftwareValidationNumber>
    <ProductID>SIF-POS</ProductID>
    <ProductVersion>1.0.4</ProductVersion>
    <Telephone> 937696096</Telephone>
    <Fax>0</Fax>
    <Email>geral@mactsystem.com</Email>
    <Website> www.mactsystem.com</Website>
  </Header>
  <MasterFiles>
    <Customer>
      <CustomerID>1</CustomerID>
      <AccountID>1</AccountID>
      <CustomerTaxID>999999999</CustomerTaxID>
      <CompanyName>Consumidor final</CompanyName>
      <Contact>0</Contact>
      <BillingAddress>
        <BuildingNumber>0</BuildingNumber>
        <StreetName>Benguela</StreetName>
        <AddressDetail>Benguela</AddressDetail>
        <City>Benguela</City>
        <Country>AO</Country>
      </BillingAddress>
      <ShipToAddress>
        <BuildingNumber>0</BuildingNumber>
        <StreetName>Benguela</StreetName>
        <AddressDetail>Benguela</AddressDetail>
        <City>Benguela</City>
        <Country>AO</Country>
      </ShipToAddress>
      <Telephone>0</Telephone>
      <SelfBillingIndicator>0</SelfBillingIndicator>
    </Customer>
    <Supplier>
      <SupplierID>1</SupplierID>
      <AccountID>1</AccountID>
      <SupplierTaxID>999999999</SupplierTaxID>
      <CompanyName>Modelo</CompanyName>
      <Contact>0123456789</Contact>
      <BillingAddress>
        <BuildingNumber>0</BuildingNumber>
        <StreetName>Bairro da Graça</StreetName>
        <AddressDetail>Bairro da Graça</AddressDetail>
        <City>Benguela</City>
        <Province>Benguela</Province>
        <Country>AO</Country>
      </BillingAddress>
      <ShipFromAddress>
        <BuildingNumber>0</BuildingNumber>
        <StreetName>Bairro da Graça</StreetName>
        <AddressDetail>Bairro da Graça</AddressDetail>
        <City>Benguela</City>
        <Province>Benguela</Province>
        <Country>AO</Country>
      </ShipFromAddress>
      <Telephone>0123456789</Telephone>
      <SelfBillingIndicator>0</SelfBillingIndicator>
    </Supplier>
    <Product>
      <ProductType>P</ProductType>
      <ProductCode>1000</ProductCode>
      <ProductGroup>ÁGUAS</ProductGroup>
      <ProductDescription>ÁGUAPURA 0.5L</ProductDescription>
      <ProductNumberCode>1000</ProductNumberCode>
    </Product>

    <TaxTable>
      <TaxTableEntry>
        <TaxType>IVA</TaxType>
        <TaxCountryRegion>AO</TaxCountryRegion>
        <TaxCode>ISE</TaxCode>
        <Description>IVA -  Regime de Não Sujeição</Description>
        <TaxPercentage>0</TaxPercentage>
      </TaxTableEntry>
    </TaxTable>
  </MasterFiles>
  <SourceDocuments>
    <SalesInvoices>
      <NumberOfEntries>2</NumberOfEntries>
      <TotalDebit>0</TotalDebit>
      <TotalCredit>2150</TotalCredit>
      <Invoice>
        <InvoiceNo>FR SIF2020/6</InvoiceNo>
        <DocumentStatus>
          <InvoiceStatus>N</InvoiceStatus>
          <InvoiceStatusDate>2020-02-18T16:52:08</InvoiceStatusDate>
          <SourceID>superuser</SourceID>
          <SourceBilling>P</SourceBilling>
        </DocumentStatus>
        <Hash>oUoB54rfoFi950U+dlVi1ZgUUy4Esr1KFIrJhRsMg/BmcdE6FHFYvaYfbx7M0a9Xqz4d+rRpFk70waVvXPZNCWVU52O87sxxWiJekZKEJlDkPU0B0THGkNgsVrTuLmqYQMXRyLrL6Dej5WKjRjBbgwpUVgJ2kLjXwDdmaizvieQ=</Hash>
        <HashControl>1</HashControl>
        <InvoiceDate>2020-02-18</InvoiceDate>
        <InvoiceType>FR</InvoiceType>
        <SpecialRegimes>
          <SelfBillingIndicator>0</SelfBillingIndicator>
          <CashVATSchemeIndicator>1</CashVATSchemeIndicator>
          <ThirdPartiesBillingIndicator>0</ThirdPartiesBillingIndicator>
        </SpecialRegimes>
        <SourceID>superuser</SourceID>
        <SystemEntryDate>2020-02-18T16:52:08</SystemEntryDate>
        <CustomerID>1</CustomerID>
        <ShipTo>
          <Address>
            <BuildingNumber>0</BuildingNumber>
            <StreetName>Benguela</StreetName>
            <AddressDetail>Benguela</AddressDetail>
            <City>Benguela</City>
            <Country>AO</Country>
          </Address>
        </ShipTo>
        <ShipFrom>
          <Address>
            <BuildingNumber>F</BuildingNumber>
            <StreetName>Rua</StreetName>
            <AddressDetail>Benguela_Angola</AddressDetail>
            <City>Benguela</City>
            <PostalCode>0</PostalCode>
            <Province>Benguela</Province>
            <Country>AO</Country>
          </Address>
        </ShipFrom>
        <Line>
          <LineNumber>1</LineNumber>
          <OrderReferences>
            <OriginatingON>1</OriginatingON>
            <OrderDate>2020-02-18</OrderDate>
          </OrderReferences>
          <ProductCode>102</ProductCode>
          <ProductDescription>PÃO DE LEITE COM FIAMBRE</ProductDescription>
          <Quantity>1.00</Quantity>
          <UnitOfMeasure>Uni</UnitOfMeasure>
          <UnitPrice>800.0000</UnitPrice>
          <TaxPointDate>2020-02-18</TaxPointDate>
          <Description>PÃO DE LEITE COM FIAMBRE</Description>
          <CreditAmount>800.0000</CreditAmount>
          <Tax>
            <TaxType>IVA</TaxType>
            <TaxCountryRegion>AO</TaxCountryRegion>
            <TaxCode>ISE</TaxCode>
            <TaxPercentage>0</TaxPercentage>
          </Tax>
          <TaxExemptionReason>IVA -  Regime de Não Sujeição</TaxExemptionReason>
          <TaxExemptionCode>M04</TaxExemptionCode>
          <SettlementAmount>0.0000</SettlementAmount>
        </Line>
        <DocumentTotals>
          <TaxPayable>0.0000</TaxPayable>
          <NetTotal>1800.00</NetTotal>
          <GrossTotal>1800</GrossTotal>
          <Payment>
            <PaymentMechanism>CC</PaymentMechanism>
            <PaymentAmount>1800.0000</PaymentAmount>
            <PaymentDate>2020-02-18</PaymentDate>
          </Payment>
        </DocumentTotals>
      </Invoice>
    </SalesInvoices>
    <Payments>
      <NumberOfEntries>1</NumberOfEntries>
      <TotalDebit>0</TotalDebit>
      <TotalCredit>1800</TotalCredit>
      <Payment>
        <PaymentRefNo>RC RC/1</PaymentRefNo>
        <Period>1</Period>
        <TransactionDate>2020-02-18</TransactionDate>
        <PaymentType>RC</PaymentType>
        <DocumentStatus>
          <PaymentStatus>N</PaymentStatus>
          <PaymentStatusDate>2020-02-18T16:52:08</PaymentStatusDate>
          <SourceID>superuser</SourceID>
          <SourcePayment>P</SourcePayment>
        </DocumentStatus>
        <PaymentMethod>
          <PaymentMechanism>CC</PaymentMechanism>
          <PaymentAmount>1800.00</PaymentAmount>
          <PaymentDate>2020-02-18</PaymentDate>
        </PaymentMethod>
        <SourceID>superuser</SourceID>
        <SystemEntryDate>2020-02-18T16:52:08</SystemEntryDate>
        <CustomerID>1</CustomerID>
        <Line>
          <LineNumber>1</LineNumber>
          <SourceDocumentID>
            <OriginatingON>1</OriginatingON>
            <InvoiceDate>2020-02-18</InvoiceDate>
          </SourceDocumentID>
          <SettlementAmount>800.0000</SettlementAmount>
          <CreditAmount>800</CreditAmount>
          <Tax>
            <TaxType>IVA</TaxType>
            <TaxCountryRegion>AO</TaxCountryRegion>
            <TaxCode>ISE</TaxCode>
            <TaxPercentage>0</TaxPercentage>
          </Tax>
          <TaxExemptionReason>IVA -  Regime de Não Sujeição</TaxExemptionReason>
          <TaxExemptionCode>M04</TaxExemptionCode>
        </Line>
        <DocumentTotals>
          <TaxPayable>0.0000</TaxPayable>
          <NetTotal>1800.00</NetTotal>
          <GrossTotal>1800.0000</GrossTotal>
          <Settlement>
            <SettlementAmount>1800.0000</SettlementAmount>
          </Settlement>
        </DocumentTotals>
      </Payment>
    </Payments>
  </SourceDocuments>
</AuditFile>
